argparser_adapter/__init__.py
argparser_adapter/implementation.py
argparser_adapter-2.2.4.dist-info/LICENSE
argparser_adapter-2.2.4.dist-info/METADATA
argparser_adapter-2.2.4.dist-info/WHEEL
argparser_adapter-2.2.4.dist-info/top_level.txt
argparser_adapter-2.2.4.dist-info/RECORD
