Metadata-Version: 2.1
Name: argparser-adapter
Version: 2.2.4
Summary: Automatically add object methods to argparser.
Home-page: https://github.com/NMRbox/argparser_adapter
Author: Gerard
Author-email: gweatherby@uchc.edu
License: MIT license
License-File: LICENSE
